[
  {
    "sigla": "AC",
    "nome": "Acre",
    "capital": "Rio Branco",
    "regiao": "North (Norte)"
  },
  {
    "sigla": "AL",
    "nome": "Alagoas",
    "capital": "Maceió",
    "regiao": "Northeast"
  },
  {
    "sigla": "AP",
    "nome": "Amapá",
    "capital": "Macapá",
    "regiao": "North (Norte)"
  },
  {
    "sigla": "AM",
    "nome": "Amazonas",
    "capital": "Manaus",
    "regiao": "North (Norte)"
  },
  {
    "sigla": "BA",
    "nome": "Bahia",
    "capital": "Salvador",
    "regiao": "Northeast"
  },
  {
    "sigla": "CE",
    "nome": "Ceará",
    "capital": "Fortaleza",
    "regiao": "Northeast"
  },
  {
    "sigla": "DF",
    "nome": "Distrito Federal",
    "capital": "Brasília",
    "regiao": "Central-West"
  },
  {
    "sigla": "ES",
    "nome": "Espírito Santo",
    "capital": "Vitória",
    "regiao": "Southeast"
  },
  {
    "sigla": "GO",
    "nome": "Goiás",
    "capital": "Goiânia",
    "regiao": "Central-West"
  },
  {
    "sigla": "MA",
    "nome": "Maranhão",
    "capital": "São Luís",
    "regiao": "Northeast"
  },
  {
    "sigla": "MT",
    "nome": "Mato Grosso",
    "capital": "Cuiabá",
    "regiao": "Central-West"
  },
  {
    "sigla": "MS",
    "nome": "Mato Grosso do South",
    "capital": "Campo Grande",
    "regiao": "Central-West"
  },
  {
    "sigla": "MG",
    "nome": "Minas Gerais",
    "capital": "Belo Horizonte",
    "regiao": "Southeast"
  },
  {
    "sigla": "PA",
    "nome": "Pará",
    "capital": "Belém",
    "regiao": "North (Norte)"
  },
  {
    "sigla": "PB",
    "nome": "Paraíba",
    "capital": "João Pessoa",
    "regiao": "Northeast"
  },
  {
    "sigla": "PR",
    "nome": "Paraná",
    "capital": "Curitiba",
    "regiao": "South"
  },
  {
    "sigla": "PE",
    "nome": "Pernambuco",
    "capital": "Recife",
    "regiao": "Northeast"
  },
  {
    "sigla": "PI",
    "nome": "Piauí",
    "capital": "Teresina",
    "regiao": "Northeast"
  },
  {
    "sigla": "RJ",
    "nome": "Rio de Janeiro",
    "capital": "Rio de Janeiro",
    "regiao": "Southeast"
  },
  {
    "sigla": "RN",
    "nome": "Rio Grande do North (Norte)",
    "capital": "Natal",
    "regiao": "Northeast"
  },
  {
    "sigla": "RS",
    "nome": "Rio Grande do South",
    "capital": "Porto Alegre",
    "regiao": "South"
  },
  {
    "sigla": "RO",
    "nome": "Rondônia",
    "capital": "Porto Velho",
    "regiao": "North (Norte)"
  },
  {
    "sigla": "RR",
    "nome": "Roraima",
    "capital": "Boa Vista",
    "regiao": "North (Norte)"
  },
  {
    "sigla": "SC",
    "nome": "Santa Catarina",
    "capital": "Florianópolis",
    "regiao": "South"
  },
  {
    "sigla": "SP",
    "nome": "São Paulo",
    "capital": "São Paulo",
    "regiao": "Southeast"
  },
  {
    "sigla": "SE",
    "nome": "Sergipe",
    "capital": "Aracaju",
    "regiao": "Northeast"
  },
  {
    "sigla": "TO",
    "nome": "Tocantins",
    "capital": "Palmas",
    "regiao": "North (Norte)"
  }
]
